stars/LICENSE
stars/README.md
stars/__init__.py
stars/constants.py
stars/controller.py
stars/instruction_constants.py
stars/lexer.py
stars/mipsParser.py
stars/preferences.json
stars/preprocess.py
stars/sbumips.py
stars/settings.py
stars/gui/__init__.py
stars/gui/mainwindow.py
stars/gui/syntaxhighlighter.py
stars/gui/textedit.py
stars/gui/theme.py
stars/gui/vt100.py
stars/gui/widgetfactory.py
stars/gui/resources/__init__.py
stars/gui/resources/assemble.svg
stars/gui/resources/assemblewhite.svg
stars/gui/resources/backstep.svg
stars/gui/resources/backstepwhite.svg
stars/gui/resources/help.svg
stars/gui/resources/helpwhite.svg
stars/gui/resources/new.svg
stars/gui/resources/newwhite.svg
stars/gui/resources/open.svg
stars/gui/resources/openwhite.svg
stars/gui/resources/pause.svg
stars/gui/resources/pausewhite.svg
stars/gui/resources/save.svg
stars/gui/resources/savewhite.svg
stars/gui/resources/start.svg
stars/gui/resources/startwhite.svg
stars/gui/resources/step.svg
stars/gui/resources/stepwhite.svg
stars/help/__init__.py
stars/help/bugs.md
stars/help/directives.csv
stars/help/help.py
stars/help/instruction_set (copy).csv
stars/help/instruction_set.csv
stars/help/instructions.csv
stars/help/operand.csv
stars/help/syscalls.csv
stars/interpreter/__init__.py
stars/interpreter/classes.py
stars/interpreter/compiled_tester.py
stars/interpreter/debugger.py
stars/interpreter/exceptions.py
stars/interpreter/instructions.py
stars/interpreter/interpreter.py
stars/interpreter/memory.py
stars/interpreter/registers.py
stars/interpreter/syscalls.py
stars/interpreter/utility.py
stars/sly/__init__.py
stars/sly/lex.py
stars/sly/yacc.py
stars/tests/__init__.py
stars/tests/test_sbumips.py
stars/tests/classes/__init__.py
stars/tests/classes/test_classes.py
stars/tests/controller/__init__.py
stars/tests/controller/test_controller.py
stars/tests/debugger/__init__.py
stars/tests/debugger/test_debugger.py
stars/tests/debugger/test_debugger_stack.py
stars/tests/fileOps/__init__.py
STARSimulator-1.0.6.dist-info/LICENSE
STARSimulator-1.0.6.dist-info/METADATA
STARSimulator-1.0.6.dist-info/WHEEL
STARSimulator-1.0.6.dist-info/entry_points.txt
STARSimulator-1.0.6.dist-info/top_level.txt
STARSimulator-1.0.6.dist-info/RECORD
