Metadata-Version: 2.1
Name: STARSimulator
Version: 1.0.6
Summary: STARS (Stony Brook Assembler and Run-time Simulator) is a MIPS Assembly simulator made for the purpose of education.
Home-page: https://github.com/sbustars/STARS
Author: STARS
Author-email: jason.osoriomarin@cs.stonybrook.edu
Project-URL: Bug Tracker, https://github.com/sbustars/STARS/issues
Classifier: Programming Language :: Python :: 3
Classifier: License :: OSI Approved :: MIT License
Classifier: Operating System :: OS Independent
Requires-Python: >=3.8
License-File: LICENSE
Requires-Dist: numpy (>=1.5)
Requires-Dist: pyside6 (>=6.4.2)
